mediafetch/__main__.py
mediafetch/template.py
mediafetch-1.5.dist-info/LICENSE
mediafetch-1.5.dist-info/METADATA
mediafetch-1.5.dist-info/WHEEL
mediafetch-1.5.dist-info/top_level.txt
mediafetch-1.5.dist-info/RECORD
