Metadata-Version: 2.1
Name: mediafetch
Version: 1.5
Summary: A media fetcher
Author: lactua
Author-email: rei.lactua.dsc@gmail.com
License-File: LICENSE
Requires-Dist: requests
Requires-Dist: pillow
